tunacode/__init__.py
tunacode/constants.py
tunacode/exceptions.py
tunacode/py.typed
tunacode/configuration/__init__.py
tunacode/configuration/defaults.py
tunacode/configuration/ignore_patterns.py
tunacode/configuration/limits.py
tunacode/configuration/models.py
tunacode/configuration/models_registry.json
tunacode/configuration/paths.py
tunacode/configuration/pricing.py
tunacode/configuration/settings.py
tunacode/configuration/user_config.py
tunacode/core/__init__.py
tunacode/core/configuration.py
tunacode/core/constants.py
tunacode/core/file_filter.py
tunacode/core/formatting.py
tunacode/core/lsp_status.py
tunacode/core/messaging.py
tunacode/core/shared_types.py
tunacode/core/state.py
tunacode/core/system_paths.py
tunacode/core/user_configuration.py
tunacode/core/agents/__init__.py
tunacode/core/agents/main.py
tunacode/core/agents/agent_components/__init__.py
tunacode/core/agents/agent_components/agent_config.py
tunacode/core/agents/agent_components/agent_helpers.py
tunacode/core/agents/agent_components/message_handler.py
tunacode/core/agents/agent_components/openai_response_validation.py
tunacode/core/agents/agent_components/response_state.py
tunacode/core/agents/agent_components/result_wrapper.py
tunacode/core/agents/agent_components/state_transition.py
tunacode/core/agents/agent_components/streaming.py
tunacode/core/agents/agent_components/tool_buffer.py
tunacode/core/agents/agent_components/tool_executor.py
tunacode/core/agents/agent_components/truncation_checker.py
tunacode/core/agents/agent_components/orchestrator/__init__.py
tunacode/core/agents/agent_components/orchestrator/message_recorder.py
tunacode/core/agents/agent_components/orchestrator/orchestrator.py
tunacode/core/agents/agent_components/orchestrator/tool_dispatcher.py
tunacode/core/agents/agent_components/orchestrator/usage_tracker.py
tunacode/core/agents/resume/__init__.py
tunacode/core/agents/resume/filter.py
tunacode/core/agents/resume/prune.py
tunacode/core/agents/resume/sanitize.py
tunacode_cli-0.1.55.dist-info/METADATA
tunacode_cli-0.1.55.dist-info/WHEEL
tunacode_cli-0.1.55.dist-info/entry_points.txt
tunacode_cli-0.1.55.dist-info/licenses/LICENSE
tunacode_cli-0.1.55.dist-info/RECORD
