Metadata-Version: 2.4
Name: tunacode-cli
Version: 0.1.55
Summary: Your agentic CLI developer.
Project-URL: Homepage, https://tunacode.xyz/
Project-URL: Repository, https://github.com/alchemiststudiosDOTai/tunacode
Project-URL: Issues, https://github.com/alchemiststudiosDOTai/tunacode/issues
Project-URL: Documentation, https://github.com/alchemiststudiosDOTai/tunacode#readme
Author-email: larock22 <noreply@github.com>
License: MIT
License-File: LICENSE
Keywords: agent,automation,cli,development
Classifier: Development Status :: 4 - Beta
Classifier: Intended Audience :: Developers
Classifier: Programming Language :: Python :: 3
Classifier: Programming Language :: Python :: 3.11
Classifier: Programming Language :: Python :: 3.12
Classifier: Programming Language :: Python :: 3.13
Classifier: Topic :: Software Development
Classifier: Topic :: Utilities
Requires-Python: <3.14,>=3.11
Requires-Dist: click<8.2.0,>=8.1.0
Requires-Dist: defusedxml
Requires-Dist: html2text>=2024.2.26
Requires-Dist: pathspec>=0.12.1
Requires-Dist: prompt-toolkit<4.0.0,>=3.0.52
Requires-Dist: pydantic-ai<2.0.0,>=1.18.0
Requires-Dist: pydantic<3.0.0,>=2.12.4
Requires-Dist: pygments<3.0.0,>=2.19.2
Requires-Dist: python-levenshtein>=0.21.0
Requires-Dist: rich<15.0.0,>=14.2.0
Requires-Dist: ruff>=0.14.0
Requires-Dist: textual-autocomplete>=4.0.6
Requires-Dist: textual<5.0.0,>=4.0.0
Requires-Dist: typer>=0.15.0
Provides-Extra: dev
Requires-Dist: autoflake>=2.0.0; extra == 'dev'
Requires-Dist: bandit; extra == 'dev'
Requires-Dist: build; extra == 'dev'
Requires-Dist: dead>=1.5.0; extra == 'dev'
Requires-Dist: mypy; extra == 'dev'
Requires-Dist: pre-commit; extra == 'dev'
Requires-Dist: pylint>=3.0.0; extra == 'dev'
Requires-Dist: pytest; extra == 'dev'
Requires-Dist: pytest-asyncio; extra == 'dev'
Requires-Dist: pytest-cov; extra == 'dev'
Requires-Dist: ruff==0.14.9; extra == 'dev'
Requires-Dist: textual-dev; extra == 'dev'
Requires-Dist: twine; extra == 'dev'
Requires-Dist: unimport>=1.0.0; extra == 'dev'
Requires-Dist: vulture>=2.7; extra == 'dev'
